pyecsca/codegen/.gitignore
pyecsca/codegen/Makefile.inc
pyecsca/codegen/__init__.py
pyecsca/codegen/action.h
pyecsca/codegen/builder.py
pyecsca/codegen/client.py
pyecsca/codegen/common.py
pyecsca/codegen/curve.h
pyecsca/codegen/fat.h
pyecsca/codegen/formulas.h
pyecsca/codegen/mult.h
pyecsca/codegen/point.h
pyecsca/codegen/rand.h
pyecsca/codegen/render.py
pyecsca/codegen/asn1/asn1.c
pyecsca/codegen/asn1/asn1.h
pyecsca/codegen/bn/bn.c
pyecsca/codegen/bn/bn.h
pyecsca/codegen/hal/Makefile.hal
pyecsca/codegen/hal/hal.h
pyecsca/codegen/hal/host/Makefile.host
pyecsca/codegen/hal/host/host_hal.c
pyecsca/codegen/hal/host/host_hal.h
pyecsca/codegen/hal/host/uart.c
pyecsca/codegen/hal/host/uart.h
pyecsca/codegen/hal/stm32f0/LinkerScript.ld
pyecsca/codegen/hal/stm32f0/Makefile.stm32f0
pyecsca/codegen/hal/stm32f0/stm32f0_hal.c
pyecsca/codegen/hal/stm32f0/stm32f0_hal.h
pyecsca/codegen/hal/stm32f0/stm32f0_hal_lowlevel.c
pyecsca/codegen/hal/stm32f0/stm32f0_hal_lowlevel.h
pyecsca/codegen/hal/stm32f0/stm32f0_startup.S
pyecsca/codegen/hal/stm32f0/stm32f0xx_hal_def.h
pyecsca/codegen/hal/stm32f0/stm32f0xx_hal_dma.h
pyecsca/codegen/hal/stm32f0/stm32f0xx_hal_dma_ex.h
pyecsca/codegen/hal/stm32f0/stm32f0xx_hal_flash.h
pyecsca/codegen/hal/stm32f0/stm32f0xx_hal_flash_ex.h
pyecsca/codegen/hal/stm32f0/stm32f0xx_hal_gpio.h
pyecsca/codegen/hal/stm32f0/stm32f0xx_hal_gpio_ex.h
pyecsca/codegen/hal/stm32f0/stm32f0xx_hal_rcc.h
pyecsca/codegen/hal/stm32f0/stm32f0xx_hal_rcc_ex.h
pyecsca/codegen/hal/stm32f0/stm32f0xx_hal_uart.h
pyecsca/codegen/hal/stm32f0/stm32f0xx_hal_uart_ex.h
pyecsca/codegen/hal/stm32f0/CMSIS/core/arm_common_tables.h
pyecsca/codegen/hal/stm32f0/CMSIS/core/arm_const_structs.h
pyecsca/codegen/hal/stm32f0/CMSIS/core/arm_math.h
pyecsca/codegen/hal/stm32f0/CMSIS/core/cmsis_armcc.h
pyecsca/codegen/hal/stm32f0/CMSIS/core/cmsis_armcc_V6.h
pyecsca/codegen/hal/stm32f0/CMSIS/core/cmsis_gcc.h
pyecsca/codegen/hal/stm32f0/CMSIS/core/core_cm0.h
pyecsca/codegen/hal/stm32f0/CMSIS/core/core_cmFunc.h
pyecsca_codegen-0.3.2.dist-info/LICENSE
pyecsca_codegen-0.3.2.dist-info/METADATA
pyecsca_codegen-0.3.2.dist-info/WHEEL
pyecsca_codegen-0.3.2.dist-info/entry_points.txt
pyecsca_codegen-0.3.2.dist-info/top_level.txt
pyecsca_codegen-0.3.2.dist-info/RECORD
