Metadata-Version: 2.1
Name: pyecsca-codegen
Version: 0.3.2
Summary: Python Elliptic Curve cryptography Side Channel Analysis toolkit (codegen package).
Author: Andrej Batora
Author-email: Jan Jancar <johny@neuromancer.sk>
Maintainer-email: Jan Jancar <johny@neuromancer.sk>
License: MIT
Project-URL: Homepage, https://pyecsca.org
Project-URL: Documentation, https://pyecsca.org
Project-URL: Bug Tracker, https://github.com/J08nY/pyecsca-codegen/issues
Project-URL: Repository, https://github.com/J08nY/pyecsca-codegen
Classifier: Development Status :: 4 - Beta
Classifier: License :: OSI Approved :: MIT License
Classifier: Topic :: Security
Classifier: Topic :: Security :: Cryptography
Classifier: Programming Language :: Python :: 3.9
Classifier: Programming Language :: Python :: 3.10
Classifier: Programming Language :: Python :: 3.11
Classifier: Programming Language :: Python :: 3.12
Classifier: Intended Audience :: Developers
Classifier: Intended Audience :: Science/Research
Requires-Python: >=3.9
License-File: LICENSE
Requires-Dist: pyecsca
Requires-Dist: chipwhisperer
Requires-Dist: numpy
Requires-Dist: scipy
Requires-Dist: atpublic
Requires-Dist: matplotlib
Requires-Dist: fastdtw
Requires-Dist: asn1crypto
Requires-Dist: jinja2
Requires-Dist: Click
Requires-Dist: importlib-resources
Requires-Dist: donjon-rainbow
Provides-Extra: dev
Requires-Dist: mypy ; extra == 'dev'
Requires-Dist: flake8 ; extra == 'dev'
Provides-Extra: test
Requires-Dist: pytest >=7.0.0 ; extra == 'test'
Requires-Dist: coverage ; extra == 'test'
Requires-Dist: pytest-cov ; extra == 'test'
Requires-Dist: pytest-sugar ; extra == 'test'
Requires-Dist: pytest-click ; extra == 'test'
